sonnerrise_tools/__init__.py
sonnerrise_tools/cli.py
sonnerrise_tools/export_service.py
sonnerrise_tools/import_service.py
sonnerrise_tools/schemas.py
sonnerrise_tools-0.1.0.dist-info/METADATA
sonnerrise_tools-0.1.0.dist-info/WHEEL
sonnerrise_tools-0.1.0.dist-info/entry_points.txt
sonnerrise_tools-0.1.0.dist-info/RECORD
