Metadata-Version: 2.4
Name: sonnerrise-tools
Version: 0.1.0
Summary: Tools module for Sonnerrise - database export/import utilities
Author-email: Konstantin Boyandin <developer@boyandin.com>
License-Expression: MIT
Requires-Python: >=3.11
Requires-Dist: pydantic>=2.0
Requires-Dist: pyyaml>=6.0
Requires-Dist: sonnerrise-core>=0.1.0
Requires-Dist: sonnerrise-definitions>=0.1.0
Requires-Dist: sonnerrise-personas>=0.1.0
Requires-Dist: sonnerrise-promo>=0.1.0
Requires-Dist: sonnerrise-tracks>=0.1.0
Provides-Extra: dev
Requires-Dist: pytest-cov>=4.0; extra == 'dev'
Requires-Dist: pytest>=7.0; extra == 'dev'
